pyx/__init__.py
pyx/pyx.py
pix_python-1.0.1.dist-info/METADATA
pix_python-1.0.1.dist-info/WHEEL
pix_python-1.0.1.dist-info/top_level.txt
pix_python-1.0.1.dist-info/RECORD
