Metadata-Version: 2.1
Name: pix-python
Version: 1.0.1
Summary: Make PIX payment codes
Author: mksDEV08
Author-email: shoultz2000@gmail.com
Keywords: python,video,stream,video stream,camera stream,sockets
Classifier: Intended Audience :: Developers
Classifier: Programming Language :: Python :: 3
Classifier: Operating System :: Unix
Classifier: Operating System :: MacOS :: MacOS X
Classifier: Operating System :: Microsoft :: Windows
Requires-Dist: opencv-python
Requires-Dist: pyautogui
Requires-Dist: pyaudio
